<?xml version="1.0" encoding="UTF-8" ?>
<Actions>
	<AudioClip>ChinaSong02</AudioClip>
	<Lane>
		<Item>
			<Time>3.05</Time>
			<Duration>0.2</Duration>
		</Item>
		<Item>
			<Time>5.93</Time>
			<Duration>0.2</Duration>
		</Item>
		<Item>
			<Time>8.255</Time>
			<Duration>0.2</Duration>
		</Item>
		<Item>
			<Time>10.538</Time>
			<Duration>0.2</Duration>
		</Item>
		<Item>
			<Time>12.053</Time>
			<Duration>0.2</Duration>
		</Item>
		<Item>
			<Time>13.141</Time>
			<Duration>0.8740005</Duration>
		</Item>
		<Item>
			<Time>17.365</Time>
			<Duration>0.2</Duration>
		</Item>
		<Item>
			<Time>18.41</Time>
			<Duration>0.2</Duration>
		</Item>
		<Item>
			<Time>20.138</Time>
			<Duration>0.2</Duration>
		</Item>
		<Item>
			<Time>21.375</Time>
			<Duration>0.2</Duration>
		</Item>
		<Item>
			<Time>22.399</Time>
			<Duration>0.2</Duration>
		</Item>
		<Item>
			<Time>25.386</Time>
			<Duration>0.2</Duration>
		</Item>
		<Item>
			<Time>25.471</Time>
			<Duration>0.2</Duration>
		</Item>
		<Item>
			<Time>26.389</Time>
			<Duration>0.2</Duration>
		</Item>
		<Item>
			<Time>27.477</Time>
			<Duration>0.2</Duration>
		</Item>
		<Item>
			<Time>27.989</Time>
			<Duration>0.2</Duration>
		</Item>
		<Item>
			<Time>29.439</Time>
			<Duration>0.2</Duration>
		</Item>
		<Item>
			<Time>30.229</Time>
			<Duration>0.2</Duration>
		</Item>
		<Item>
			<Time>31.466</Time>
			<Duration>0.2</Duration>
		</Item>
		<Item>
			<Time>32.17</Time>
			<Duration>0.2</Duration>
		</Item>
		<Item>
			<Time>33.173</Time>
			<Duration>0.2</Duration>
		</Item>
	</Lane>
	<Lane>
		<Item>
			<Time>4.053</Time>
			<Duration>0.2</Duration>
		</Item>
		<Item>
			<Time>5.418</Time>
			<Duration>0.2</Duration>
		</Item>
		<Item>
			<Time>7.637</Time>
			<Duration>0.2</Duration>
		</Item>
		<Item>
			<Time>10.282</Time>
			<Duration>0.2</Duration>
		</Item>
		<Item>
			<Time>14.805</Time>
			<Duration>1.172999</Duration>
		</Item>
		<Item>
			<Time>18.879</Time>
			<Duration>0.2</Duration>
		</Item>
		<Item>
			<Time>22.975</Time>
			<Duration>0.2</Duration>
		</Item>
		<Item>
			<Time>23.999</Time>
			<Duration>0.2</Duration>
		</Item>
		<Item>
			<Time>26.197</Time>
			<Duration>0.2</Duration>
		</Item>
		<Item>
			<Time>29.141</Time>
			<Duration>0.2</Duration>
		</Item>
		<Item>
			<Time>30.826</Time>
			<Duration>0.2</Duration>
		</Item>
		<Item>
			<Time>31.103</Time>
			<Duration>0.2</Duration>
		</Item>
		<Item>
			<Time>32.639</Time>
			<Duration>0.2</Duration>
		</Item>
	</Lane>
	<Lane>
		<Item>
			<Time>4.991</Time>
			<Duration>0.2</Duration>
		</Item>
		<Item>
			<Time>7.103</Time>
			<Duration>0.2</Duration>
		</Item>
		<Item>
			<Time>9.279</Time>
			<Duration>0.2</Duration>
		</Item>
		<Item>
			<Time>11.029</Time>
			<Duration>0.2</Duration>
		</Item>
		<Item>
			<Time>16.789</Time>
			<Duration>0.2</Duration>
		</Item>
		<Item>
			<Time>17.983</Time>
			<Duration>0.2</Duration>
		</Item>
		<Item>
			<Time>19.519</Time>
			<Duration>0.2</Duration>
		</Item>
		<Item>
			<Time>20.778</Time>
			<Duration>0.2</Duration>
		</Item>
		<Item>
			<Time>21.695</Time>
			<Duration>0.2</Duration>
		</Item>
		<Item>
			<Time>23.487</Time>
			<Duration>0.2</Duration>
		</Item>
		<Item>
			<Time>25.919</Time>
			<Duration>0.2</Duration>
		</Item>
		<Item>
			<Time>26.879</Time>
			<Duration>0.2</Duration>
		</Item>
		<Item>
			<Time>28.501</Time>
			<Duration>0.2</Duration>
		</Item>
		<Item>
			<Time>29.695</Time>
			<Duration>0.2</Duration>
		</Item>
		<Item>
			<Time>30.527</Time>
			<Duration>0.2</Duration>
		</Item>
		<Item>
			<Time>31.765</Time>
			<Duration>0.2</Duration>
		</Item>
		<Item>
			<Time>34.005</Time>
			<Duration>0.2</Duration>
		</Item>
	</Lane>
</Actions>
